vinum_lib.cpython-38-x86_64-linux-gnu.so
libvinum_cpp.a
vinum/__init__.py
vinum/_version.py
vinum/_typing.py
vinum/parser/query.py
vinum/parser/__init__.py
vinum/parser/parser.py
vinum/io/arrow.py
vinum/io/__init__.py
vinum/util/tree_print.py
vinum/util/util.py
vinum/util/__init__.py
vinum/api/stream_reader.py
vinum/api/table.py
vinum/api/__init__.py
vinum/planner/binder.py
vinum/planner/__init__.py
vinum/planner/planner.py
vinum/errors/__init__.py
vinum/tests/test_table_api.py
vinum/tests/conftest.py
vinum/tests/test_query_results.py
vinum/tests/__init__.py
vinum/tests/test_io.py
vinum/tests/test_sql_syntax_tree.py
vinum/arrow/record_batch.py
vinum/arrow/arrow_table.py
vinum/arrow/__init__.py
vinum/executor/executor.py
vinum/executor/__init__.py
vinum/core/udf.py
vinum/core/functions.py
vinum/core/base.py
vinum/core/__init__.py
vinum/core/sql_operators_mapping.py
vinum/core/aggregate.py
vinum/core/algebra.py
vinum.libs/libarrow_python-d8e20ac6.so.300
vinum.libs/libarrow-2c5dc7b6.so.300
vinum-0.3.2.dist-info/WHEEL
vinum-0.3.2.dist-info/top_level.txt
vinum-0.3.2.dist-info/RECORD
vinum-0.3.2.dist-info/METADATA
vinum-0.3.2.dist-info/LICENSE
