Metadata-Version: 2.1
Name: vinum
Version: 0.3.2
Summary: Vinum is a SQL query processor for Python, designed for data analysis workflows and in-memory analytics.
Home-page: https://github.com/dmitrykoval/vinum
Author: Dmitry Koval
Author-email: dima@koval.space
License: UNKNOWN
Project-URL: Bug Tracker, https://github.com/dmitrykoval/vinum/issues
Project-URL: Documentation, https://vinum.readthedocs.io/en/latest/index.html
Project-URL: Source Code, https://github.com/dmitrykoval/vinum
Keywords: sql,python,numpy,data analysis,olap
Platform: UNKNOWN
Classifier: Development Status :: 3 - Alpha
Classifier: Environment :: Console
Classifier: Operating System :: OS Independent
Classifier: Intended Audience :: Science/Research
Classifier: Programming Language :: Python
Classifier: Programming Language :: Python :: 3
Classifier: Programming Language :: Python :: 3.7
Classifier: Programming Language :: Python :: 3.8
Classifier: Programming Language :: SQL
Classifier: Topic :: Scientific/Engineering
Requires-Python: >=3.7
